hgchat/__init__.py
hgchat-0.1.3.dist-info/METADATA
hgchat-0.1.3.dist-info/WHEEL
hgchat-0.1.3.dist-info/RECORD
